setup.py
django_jadelesscoffee.egg-info/PKG-INFO
django_jadelesscoffee.egg-info/SOURCES.txt
django_jadelesscoffee.egg-info/dependency_links.txt
django_jadelesscoffee.egg-info/requires.txt
django_jadelesscoffee.egg-info/top_level.txt
jadelesscoffee/__init__.py
jadelesscoffee/django/__init__.py
jadelesscoffee/django/middleware.py