Metadata-Version: 1.1
Name: django-jadelesscoffee
Version: 0.3.0
Summary: Django middleware class that executes the Node.js JadeLessCoffee compiler on a `src` folder in the TEMPLATE_DIRS directory.
Home-page: http://github.com/Nuulogic/django-jadelesscoffee/
Author: Oliver Wilkerson, Matthew Wells, Jeff Andrews, Nuu Logic LLC
Author-email: oliver.wilkerson@gmail.com
License: UNKNOWN
Keywords: django,jade,less,lesscss,coffeescript,nodejs,node,npm,coffee,jlc,middleware
Platform: UNKNOWN
Classifier: Development Status :: 4 - Beta
Classifier: Framework :: Django
Classifier: Intended Audience :: Developers
Classifier: License :: OSI Approved :: GNU General Public License v3 or later (GPLv3+)
Classifier: Operating System :: OS Independent
Classifier: Programming Language :: Python
Classifier: Programming Language :: JavaScript
